py_pkg_logging/__init__.py
py_pkg_logging/__version__.py
py_pkg_logging/_log_config.py
py_pkg_logging/_log_function_call.py
py_pkg_logging/_packing_logging.py
py_pkg_logging-0.0.3.dist-info/METADATA
py_pkg_logging-0.0.3.dist-info/WHEEL
py_pkg_logging-0.0.3.dist-info/top_level.txt
py_pkg_logging-0.0.3.dist-info/RECORD
