Metadata-Version: 2.1
Name: py_pkg_logging
Version: 0.0.3
Summary: Python Package Logging Assistant.
Home-page: https://github.com/mvinyard/py-pkg-logging
Author: Michael E. Vinyard
Author-email: mvinyard.ai@gmail.com
License: MIT
Classifier: Development Status :: 2 - Pre-Alpha
Classifier: Programming Language :: Python :: 3.9
Classifier: Intended Audience :: Science/Research
Classifier: Topic :: Scientific/Engineering :: Bio-Informatics
Requires-Python: >3.9.0
Requires-Dist: ABCParse >=0.0.8
